venom/__init__.py
venom/venom.py
kmy_venom-0.2.0.dist-info/METADATA
kmy_venom-0.2.0.dist-info/WHEEL
kmy_venom-0.2.0.dist-info/entry_points.txt
kmy_venom-0.2.0.dist-info/top_level.txt
kmy_venom-0.2.0.dist-info/RECORD
