Metadata-Version: 2.1
Name: kmy-venom
Version: 0.2.0
Summary: bind blackdoor into apk/exe file.
Home-page: https://github.com/ExsoKamabay/venom
Author: Exso Kamabay
License: Apache License 2.0
Keywords: kamabay,venom
Platform: UNKNOWN
Classifier: License :: OSI Approved :: Apache Software License
Classifier: Operating System :: OS Independent
Classifier: Programming Language :: Python :: 3
Classifier: Topic :: Utilities
Requires-Dist: bs4
Requires-Dist: kmy-beautify (==0.6.0)
Requires-Dist: requests
